[
  {
    "name": "harrison yim",
    "id": "550e8400-e29b-41d4-a716-446655440000",
    "email": "harrison@example.com",
    "lessons": [
      {
        "id": "123e4567-e89b-12d3-a456-426614174000",
        "title": "Basic Chords",
        "song": "Twinkle Twinkle Little Star",
        "difficulty": 1,
        "rating": 4.5,
        "performanceScore": 80
      }
    ],
    "level": 3,
    "achievements": ["First Song Played", "Perfect Score"]
  },
  {
    "name": "tj beeks",
    "id": "b0386f84-6e8f-4675-9ef1-e53cf26eafdd",
    "email": "tj@example.com",
    "lessons": [
      {
        "id": "9ad47a3e-43e6-4609-b34e-7dd0953a19b0",
        "title": "Intermediate Chords",
        "song": "Mary Had a Little Lamb",
        "difficulty": 2,
        "rating": 4.2,
        "performanceScore": 75
      }
    ],
    "level": 4,
    "achievements": ["First Song Played"]
  },
  {
    "name": "damien dobbins",
    "id": "301959e4-0f92-4787-9ea7-79a84c62eb21",
    "email": "damien@example.com",
    "lessons": [
      {
        "id": "5b517d35-ac04-484a-8784-a40513fa7a9d",
        "title": "Advanced Melody",
        "song": "Fur Elise",
        "difficulty": 3,
        "rating": 4.8,
        "performanceScore": 90
      }
    ],
    "level": 5,
    "achievements": ["First Song Played", "Perfect Score", "Master Pianist"]
  }
]